pyconverter/xml2py/__init__.py
pyconverter/xml2py/ast_tree.py
pyconverter/xml2py/cli.py
pyconverter/xml2py/custom_functions.py
pyconverter/xml2py/directory_format.py
pyconverter/xml2py/download.py
pyconverter/xml2py/formatter.py
pyconverter/xml2py/load_xml_doc.py
pyconverter/xml2py/version_variables.py
pyconverter/xml2py/writer.py
pyconverter/xml2py/utils/__init__.py
pyconverter/xml2py/utils/regex_pattern.py
pyconverter/xml2py/utils/utils.py
pyconverter_xml2py-0.3.0.dist-info/entry_points.txt
pyconverter_xml2py-0.3.0.dist-info/LICENSE
pyconverter_xml2py-0.3.0.dist-info/WHEEL
pyconverter_xml2py-0.3.0.dist-info/METADATA
pyconverter_xml2py-0.3.0.dist-info/RECORD
