Metadata-Version: 2.1
Name: pyconverter-xml2py
Version: 0.3.0
Summary: PyConverter-XML2Py converter.
Author-email: "ANSYS, Inc." <pyansys.core@ansys.com>
Maintainer-email: PyAnsys Core <pyansys.core@ansys.com>
Requires-Python: >=3.10,<4
Classifier: Development Status :: 4 - Beta
Classifier: License :: OSI Approved :: MIT License
Classifier: Operating System :: OS Independent
Classifier: Programming Language :: Python :: 3.10
Classifier: Programming Language :: Python :: 3.11
Classifier: Programming Language :: Python :: 3.12
Requires-Dist: click>=7.0,<9.0.0
Requires-Dist: importlib-metadata>=4.0
Requires-Dist: pygithub>=1.59.1
Requires-Dist: inflect>=7.0.0
Requires-Dist: lxml>=4.9.3
Requires-Dist: numpy>=1.14.0
Requires-Dist: py-asciimath==0.3.0
Requires-Dist: pylatexenc==2.10
Requires-Dist: pyyaml>=5.1.0
Requires-Dist: tqdm>=4.64.1
Requires-Dist: black>=24.2.0
Requires-Dist: regex>=2021.4.4
Requires-Dist: Sphinx==8.0.2 ; extra == "doc"
Requires-Dist: ansys-sphinx-theme[autoapi]==1.1.5 ; extra == "doc"
Requires-Dist: build>= 0.10.0 ; extra == "doc"
Requires-Dist: flit>=3.8.0 ; extra == "doc"
Requires-Dist: inflect==7.4.0 ; extra == "doc"
Requires-Dist: jupyter_sphinx==0.5.3 ; extra == "doc"
Requires-Dist: numpy==2.1.2 ; extra == "doc"
Requires-Dist: numpydoc==1.8.0 ; extra == "doc"
Requires-Dist: pandas==2.2.3 ; extra == "doc"
Requires-Dist: parse==1.20.2 ; extra == "doc"
Requires-Dist: pypandoc==1.13 ; extra == "doc"
Requires-Dist: pytest-sphinx==0.6.3 ; extra == "doc"
Requires-Dist: regex==2024.9.11 ; extra == "doc"
Requires-Dist: sphinx-autobuild==2024.9.19 ; extra == "doc"
Requires-Dist: sphinx-autodoc-typehints==2.4.4 ; extra == "doc"
Requires-Dist: sphinx-copybutton==0.5.2 ; extra == "doc"
Requires-Dist: sphinx-notfound-page==1.0.4 ; extra == "doc"
Requires-Dist: sphinx-gallery==0.17.1 ; extra == "doc"
Requires-Dist: black>=24.2.0 ; extra == "tests"
Requires-Dist: click==8.1.7 ; extra == "tests"
Requires-Dist: inflect==7.4.0 ; extra == "tests"
Requires-Dist: pygithub==2.4.0 ; extra == "tests"
Requires-Dist: lxml==5.3.0 ; extra == "tests"
Requires-Dist: numpy==2.1.2 ; extra == "tests"
Requires-Dist: parse==1.20.2 ; extra == "tests"
Requires-Dist: pytest==8.3.3 ; extra == "tests"
Requires-Dist: pytest-cov==5.0.0 ; extra == "tests"
Requires-Dist: pytest-rerunfailures==14.0 ; extra == "tests"
Requires-Dist: pyyaml==6.0.2 ; extra == "tests"
Requires-Dist: regex==2024.9.11 ; extra == "tests"
Project-URL: Homepage, https://github.com/ansys/pyconverter-xml2py
Project-URL: Source, https://github.com/ansys/pyconverter-xml2py/
Project-URL: Tracker, https://github.com/ansys/pyconverter-xml2py/issues
Provides-Extra: doc
Provides-Extra: tests
